.travis.yml
CHANGELOG.md
CHANGELOG.rst
MANIFEST.in
README.md
README.rst
requirements.txt
setup.py
cletus/__init__.py
cletus/_version.py
cletus/cletus_config.py
cletus/cletus_job.py
cletus/cletus_job_extras.py
cletus/cletus_log.py
cletus/cletus_supp.py
cletus.egg-info/PKG-INFO
cletus.egg-info/SOURCES.txt
cletus.egg-info/dependency_links.txt
cletus.egg-info/requires.txt
cletus.egg-info/top_level.txt
docs/CURRENT_RELEASE_NOTES
docs/TO_DO
example/cletus_archiver_config.yml
scripts/cletus_archiver.py