Metadata-Version: 1.1
Name: cletus
Version: 1.0.15
Summary: A library of command line utilities
Home-page: http://github.com/kenfar/cletus
Author: Ken Farmer
Author-email: kenfar@gmail.com
License: BSD
Keywords: utility
Platform: UNKNOWN
Classifier: Development Status :: 4 - Beta
Classifier: Environment :: Console
Classifier: Intended Audience :: Developers
Classifier: License :: OSI Approved :: BSD License
Classifier: Programming Language :: Python
Classifier: Programming Language :: Python :: 2.7
Classifier: Programming Language :: Python :: 3
Classifier: Programming Language :: Python :: 3.4
Classifier: Programming Language :: Python :: Implementation :: CPython
Classifier: Programming Language :: Python :: Implementation :: PyPy
Classifier: Operating System :: POSIX
Classifier: Topic :: Utilities
